ambee_sdk/__init__.py
ambee_sdk/ambee_sdk.py
ambee_sdk-0.1.1.dist-info/LICENSE
ambee_sdk-0.1.1.dist-info/METADATA
ambee_sdk-0.1.1.dist-info/WHEEL
ambee_sdk-0.1.1.dist-info/top_level.txt
ambee_sdk-0.1.1.dist-info/RECORD
