Metadata-Version: 2.1
Name: ambee-sdk
Version: 0.1.1
Summary: Python SDK for Ambee's APIs
Home-page: 
Author: Ambee
License: MIT
Keywords: ambee climate environment pollen air-quality weather api sdk
Classifier: Development Status :: 4 - Beta
Classifier: Intended Audience :: Developers
Classifier: License :: OSI Approved :: MIT License
Classifier: Programming Language :: Python :: 3.10
License-File: LICENSE
Requires-Dist: requests
Requires-Dist: pandas
Requires-Dist: geopandas
